[
  {
    "location_area": {
      "name": "alola-route-1-hauoli-outskirts"
    },
    "version_details": [
      {
        "version": {
          "name": "sun"
        },
        "encounter_details": [
          {
            "method": {
              "name": "walk"
            },
            "condition_values": []
          }
        ]
      },
      {
        "version": {
          "name": "moon"
        },
        "encounter_details": [
          {
            "method": {
              "name": "walk"
            },
            "condition_values": []
          }
        ]
      }
    ]
  },
  {
    "location_area": {
      "name": "alola-route-1-trainers-school"
    },
    "version_details": [
      {
        "version": {
          "name": "ultra-sun"
        },
        "encounter_details": [
          {
            "method": {
              "name": "walk"
            },
            "condition_values": []
          }
        ]
      },
      {
        "version": {
          "name": "ultra-moon"
        },
        "encounter_details": [
          {
            "method": {
              "name": "walk"
            },
            "condition_values": []
          }
        ]
      }
    ]
  },
  {
    "location_area": {
      "name": "hauoli-city-shopping-district"
    },
    "version_details": [
      {
        "version": {
          "name": "sun"
        },
        "encounter_details": [
          {
            "method": {
              "name": "walk"
            },
            "condition_values": []
          }
        ]
      },
      {
        "version": {
          "name": "moon"
        },
        "encounter_details": [
          {
            "method": {
              "name": "walk"
            },
            "condition_values": []
          }
        ]
      },
      {
        "version": {
          "name": "ultra-sun"
        },
        "encounter_details": [
          {
            "method": {
              "name": "walk"
            },
            "condition_values": []
          }
        ]
      },
      {
        "version": {
          "name": "ultra-moon"
        },
        "encounter_details": [
          {
            "method": {
              "name": "walk"
            },
            "condition_values": []
          }
        ]
      }
    ]
  },
  {
    "location_area": {
      "name": "malie-city-outer-cape"
    },
    "version_details": [
      {
        "version": {
          "name": "sun"
        },
        "encounter_details": [
          {
            "method": {
              "name": "walk"
            },
            "condition_values": []
          }
        ]
      },
      {
        "version": {
          "name": "moon"
        },
        "encounter_details": [
          {
            "method": {
              "name": "walk"
            },
            "condition_values": []
          }
        ]
      },
      {
        "version": {
          "name": "ultra-sun"
        },
        "encounter_details": [
          {
            "method": {
              "name": "walk"
            },
            "condition_values": []
          }
        ]
      },
      {
        "version": {
          "name": "ultra-moon"
        },
        "encounter_details": [
          {
            "method": {
              "name": "walk"
            },
            "condition_values": []
          }
        ]
      }
    ]
  }
]