[
  {
    "location_area": {
      "name": "nature-sanctuary-area"
    },
    "version_details": [
      {
        "version": {
          "name": "black-2"
        },
        "encounter_details": [
          {
            "method": {
              "name": "only-one"
            },
            "condition_values": []
          }
        ]
      },
      {
        "version": {
          "name": "white-2"
        },
        "encounter_details": [
          {
            "method": {
              "name": "only-one"
            },
            "condition_values": []
          }
        ]
      }
    ]
  }
]